index/__init__.py
index/kd_tree.py
search/__init__.py
search/nearest_neighbor.py
similarity/__init__.py
similarity/cosine_similarity.py
similarity/quantum_cosine_similarity.py
tests/__init__.py
vector_representation/__init__.py
vector_representation/audio_vectorizer.py
vector_representation/image_vectorizer.py
vector_representation/text_vectorizer.py
StateVector-0.1.dist-info/METADATA
StateVector-0.1.dist-info/WHEEL
StateVector-0.1.dist-info/top_level.txt
StateVector-0.1.dist-info/RECORD
