Metadata-Version: 2.1
Name: StateVector
Version: 0.1
Summary: A vector database optimized for cosine similarity using quantum algorithms
Home-page: https://github.com/crystal-tensor/StateVector
Author: Your Name
Author-email: your.email@example.com
Classifier: Programming Language :: Python :: 3
Classifier: License :: OSI Approved :: MIT License
Classifier: Operating System :: OS Independent
Requires-Python: >=3.6
Requires-Dist: numpy
Requires-Dist: scipy
